lumafit/__init__.py
lumafit-0.2.3.dist-info/METADATA
lumafit-0.2.3.dist-info/WHEEL
lumafit-0.2.3.dist-info/licenses/LICENSE
lumafit-0.2.3.dist-info/RECORD
