Metadata-Version: 2.4
Name: lumafit
Version: 0.2.3
Summary: A Numba-accelerated Levenberg-Marquardt fitting library
Author-email: Mirza Arnaut <mirza.arnaut@tu-dortmund.de>
License: MIT
License-File: LICENSE
Keywords: fitting,least-squares,levenberg-marquardt,numba,optimization,scientific
Requires-Python: >=3.10
Requires-Dist: numba>=0.61.0
Requires-Dist: numpy>=1.26
Requires-Dist: scipy>=1.15.3
